<?xml version="1.0" encoding="UTF-8" standalone="yes"?>
<employees>
    <employee>
        <dept>
            <id>2</id>
            <name>GCE</name>
        </dept>
        <designation>TechLead</designation>
        <empid>659</empid>
        <hobbies>teaching,singing</hobbies>
        <id>5</id>
        <name>Tabish</name>
        <salary>40000</salary>
    </employee>
    <employee>
        <dept>
            <id>3</id>
            <name>Training</name>
        </dept>
        <designation>Trainee</designation>
        <empid>547</empid>
        <hobbies>cricket,football</hobbies>
        <id>1</id>
        <name>Saqlain</name>
        <salary>10000</salary>
    </employee>
    <employee>
        <dept>
            <id>2</id>
            <name>GCE</name>
        </dept>
        <designation>SDE</designation>
        <empid>368</empid>
        <hobbies>swimming,football</hobbies>
        <id>2</id>
        <name>Mohit</name>
        <salary>20000</salary>
    </employee>
    <employee>
        <dept>
            <id>3</id>
            <name>Training</name>
        </dept>
        <designation>Trainee</designation>
        <empid>652</empid>
        <hobbies>music,dance</hobbies>
        <id>3</id>
        <name>Vikas</name>
        <salary>10000</salary>
    </employee>
    <employee>
        <dept>
            <id>4</id>
            <name>Flights</name>
        </dept>
        <designation>CTO</designation>
        <empid>845</empid>
        <hobbies>trekking,teaching</hobbies>
        <id>4</id>
        <name>Nikhil</name>
        <salary>50000</salary>
    </employee>
</employees>
